deserial/__main__.py
deserial/errors.py
deserial/util.py
deserial-0.1.3.dist-info/entry_points.txt
deserial-0.1.3.dist-info/METADATA
deserial-0.1.3.dist-info/WHEEL
deserial-0.1.3.dist-info/RECORD
