Metadata-Version: 2.1
Name: deserial
Version: 0.1.3
Summary: 
Author: Bohdan Vanieiev
Author-email: warchantua@gmail.com
Requires-Python: >=3.9,<4.0
Classifier: Programming Language :: Python :: 3
Classifier: Programming Language :: Python :: 3.9
Classifier: Programming Language :: Python :: 3.10
Classifier: Programming Language :: Python :: 3.11
Classifier: Programming Language :: Python :: 3.12
Requires-Dist: coloredlogs (>=15.0.1,<16.0.0)
Requires-Dist: dataclass-factory (>=2.16,<3.0)
Requires-Dist: pyserial (>=3.5,<4.0)
Requires-Dist: pyyaml (>=6.0.1,<7.0.0)
